setup.cfg
setup.py
resourceguruscripts/__init__.py
resourceguruscripts/resourceguruscripts.py
resourceguruscripts.egg-info/PKG-INFO
resourceguruscripts.egg-info/SOURCES.txt
resourceguruscripts.egg-info/dependency_links.txt
resourceguruscripts.egg-info/pbr.json
resourceguruscripts.egg-info/top_level.txt