Metadata-Version: 1.1
Name: resourceguruscripts
Version: 0.8.12
Summary: ResourceGuru Python for Scripts
Home-page: https://github.com/andybp85/resourceguruscripts
Author: Andrew Stanish for YouShallThrive, Inc. based on original by Owen Barton
Author-email: andy@youshallthrive.com
License: UNKNOWN
Download-URL: https://github.com/andybp85/resourceguruscripts/tarball/0.8.12
Keywords: resourceguru
Platform: UNKNOWN
Requires: requests_oauthlib
